cformers/__init__.py
cformers/chat.py
cformers/interface.py
cformers/pythia.py
cformers/test_return_logits.py
cformers/cpp/Makefile
cformers/cpp/__init__.py
cformers/cpp/ggml.c
cformers/cpp/ggml.h
cformers/cpp/ggml.o
cformers/cpp/main
cformers/cpp/main.cpp
cformers/cpp/quantize_bloom
cformers/cpp/quantize_bloom.cpp
cformers/cpp/quantize_gpt2
cformers/cpp/quantize_gpt2.cpp
cformers/cpp/quantize_gptj
cformers/cpp/quantize_gptj.cpp
cformers/cpp/quantize_gptneox
cformers/cpp/quantize_gptneox.cpp
cformers/cpp/utils.cpp
cformers/cpp/utils.h
cformers/cpp/utils.o
cformers-0.0.4.dist-info/LICENSE
cformers-0.0.4.dist-info/METADATA
cformers-0.0.4.dist-info/WHEEL
cformers-0.0.4.dist-info/top_level.txt
cformers-0.0.4.dist-info/RECORD
