Metadata-Version: 2.1
Name: cformers
Version: 0.0.4
Summary: SoTA Transformers with C-backend for fast inference on your CPU.
Author: Ayush Kaushal (Ayushk4)
Author-email: ayush4@utexas.edu
Keywords: python,local inference,c++ inference,language models,cpu inference,quantization
Classifier: Development Status :: 2 - Pre-Alpha
Classifier: Intended Audience :: Developers
Classifier: Programming Language :: Python :: 3
Classifier: Operating System :: Unix
Classifier: Operating System :: MacOS :: MacOS X
Classifier: Operating System :: Microsoft :: Windows
License-File: LICENSE
Requires-Dist: transformers
Requires-Dist: torch
Requires-Dist: wget
